togou/RedisQueue.py
togou/__init__.py
togou/file_writer.py
togou-0.1.2.dist-info/licenses/LICENSE
togou-0.1.2.dist-info/METADATA
togou-0.1.2.dist-info/WHEEL
togou-0.1.2.dist-info/top_level.txt
togou-0.1.2.dist-info/RECORD
